{
  "Δθ": {
    "nome": "Variação de Temperatura",
    "mascara": "Δθ",
    "unidade":"Kelvin(s)"
  },
  "Δθ''": {
    "nome": "Temperatura Final",
    "mascara": "Δθ''",
    "unidade":"Kelvin(s)"
  },
  "Δθ'": {
    "nome": "Temperatura Inicial",
    "mascara": "Δθ'",
    "unidade":"Kelvin(s)"
  },
  "Δθc": {
    "nome": "Variação de Temperatura em Celsius",
    "mascara": "Δθc",
    "unidade":"Celsius"
  },
  "Δθf": {
    "nome": "Variação de Temperatura em Fahrenheit",
    "mascara": "Δθf",
    "unidade":"Fahrenheit"
  },
  "Δθk": {
    "nome": "Variação de Temperatura em Kelvin",
    "mascara": "Δθk",
    "unidade":"Kelvin"
  },
  "ΔL": {
    "nome": "Variação de Comprimento",
    "mascara": "ΔL",
    "unidade":"Metro(s)"
  },
  "L0": {
    "nome": "Comprimento Inicial",
    "mascara": "L0",
    "unidade":"Metro(s)"
  },
  "α": {
    "nome": "Coeficiente de Dilatação Linear",
    "mascara": "α",
    "unidade":"Celsius Recíproco"
  },
  "ΔA": {
    "nome": "Variação de Área",
    "mascara": "ΔA",
    "unidade":"Metro(s) ao quadrado"
  },
  "A0": {
    "nome": "Área Inicial",
    "mascara": "A0",
    "unidade":"Metro(s) ao quadrado"
  },
  "ΔV": {
    "nome": "Variação de Volume(Sólido e Líquido)",
    "mascara": "ΔV",
    "unidade":"Metro(s) ao cubo"
  },
  "V0": {
    "nome": "Volume Inicial",
    "mascara": "V0",
    "unidade":"Metro(s) ao cubo"
  },
  "ΔVap": {
    "nome": "Variação da Dilatação Aparente",
    "mascara": "ΔVap",
    "unidade":"Metro(s) ao cubo"
  },
  "ΔVf": {
    "nome": "Variação da Dilatação do Frasco",
    "mascara": "ΔVf",
    "unidade":"Metro(s) ao cubo"
  },
  "C": {
    "nome": "Capacidade Térmica",
    "mascara": "C",
    "unidade":"Caloria(s) por Celsius"
  },
  "c": {
    "nome": "Calor Específico",
    "mascara": "c",
    "unidade":"Joule(s) por Quilo Kelvin"
  },
  "m": {
    "nome": "Massa",
    "mascara": "m",
    "unidade":"Quilo"
  },
  "Q": {
    "nome": "Quantidade de Calor Sensível",
    "mascara": "Q",
    "unidade":"Caloria(s) por Grama Celsius"
  },
  "L": {
    "nome": "Calor Latente",
    "mascara": "L",
    "unidade":"Joule(s) por Quilo"
  },
  "Qc": {
    "nome": "Quantidade de Calor Cedido",
    "mascara": "Qc",
    "unidade":"Caloria(s)"
  },
  "Qr": {
    "nome": "Quantidade de Calor Recebido",
    "mascara": "Qr",
    "unidade":"Caloria(s)"
  },
  "Φ": {
    "nome": "Fluxo de Calor",
    "mascara": "Φ",
    "unidade":"Watts por Metro elevado na -2"
  },
   "p": {
    "nome": "Pressão",
    "mascara": "p",
    "unidade":"Newton(s) por Metro ao quadrado"
  },
   "V": {
    "nome": "Volume",
    "mascara": "V",
    "unidade":"Metro(s) ao cubo"
  },
  "n": {
    "nome": "numero de mols",
    "mascara": "n",
    "unidade":"Mol(es)"
  },
  "R": {
    "nome": "Constante Universal dos Gases Perfeitos",
    "mascara": "R",
    "unidade":"Joule(s) por Mol Kelvin"
  },
  "T": {
    "nome": "Temperatura",
    "mascara": "T",
    "unidade":"Kelvin"
  },
   "p'": {
    "nome": "Pressão '",
    "mascara": "p'",
    "unidade":"Newton(s) por Metro ao quadrado"
  },
   "V'": {
    "nome": "Volume '",
    "mascara": "V'",
    "unidade":"Metro(s) ao cubo"
  },
  "T'": {
    "nome": "Temperatura '",
    "mascara": "T'",
    "unidade":"Kelvin"
  },
   "τ": {
    "nome": "Trabalho",
    "mascara": "τ",
    "unidade":"Joule(s)"
  },
   "ΔU": {
    "nome": "Variação de Energia Interna",
    "mascara": "ΔU",
    "unidade":"Joule(s)"
  },
  "Qq": {
    "nome": "Fonte Quente",
    "mascara": "Qq",
    "unidade":"Joule(s)"
  },
  "Qf": {
    "nome": "Fonte Fria",
    "mascara": "Qf",
    "unidade":"Joule(s)"
  },
   "η": {
    "nome": "Rendimento",
    "mascara": "η",
    "unidade":""
  },
  "Tq": {
    "nome": "Fonte Quente",
    "mascara": "Tq",
    "unidade":"Kelvin"
  },
  "Tf": {
    "nome": "Fonte Fria",
    "mascara": "Tf",
    "unidade":"Kelvin"
  }
}